LICENSE.txt
MANIFEST.in
README.rst
setup.py
rotate_backups_s3/__init__.py
rotate_backups_s3/cli.py
rotate_backups_s3.egg-info/PKG-INFO
rotate_backups_s3.egg-info/SOURCES.txt
rotate_backups_s3.egg-info/dependency_links.txt
rotate_backups_s3.egg-info/entry_points.txt
rotate_backups_s3.egg-info/requires.txt
rotate_backups_s3.egg-info/top_level.txt