Metadata-Version: 1.1
Name: rotate-backups-s3
Version: 0.3
Summary: Simple command line interface for S3 backup rotation
Home-page: https://github.com/tarzan0820/python-rotate-backups-s3
Author: Salton Massally
Author-email: salton.massally@gmail.com
License: UNKNOWN
Platform: UNKNOWN
Classifier: Development Status :: 5 - Production/Stable
Classifier: Environment :: Console
Classifier: Intended Audience :: Developers
Classifier: Intended Audience :: System Administrators
Classifier: License :: OSI Approved :: MIT License
Classifier: Operating System :: POSIX
Classifier: Operating System :: Unix
Classifier: Programming Language :: Python
Classifier: Programming Language :: Python :: 2
Classifier: Programming Language :: Python :: 2.7
Classifier: Programming Language :: Python :: Implementation :: CPython
Classifier: Programming Language :: Python :: Implementation :: PyPy
Classifier: Topic :: Software Development :: Libraries :: Python Modules
Classifier: Topic :: Software Development
Classifier: Topic :: System :: Archiving :: Backup
Classifier: Topic :: System :: Systems Administration
